{
  "slug": "hanoi",
  "name": "Hanoi",
  "categories": [
    "general"
  ],
  "implementations": {
    "rust": "",
    "julia": ""
  },
  "contributors": [
    {
      "name": "Arnav Borborah",
      "email": "arnavborborah11@gmail.com",
      "commits": 1
    },
    {
      "name": "lukabavdaz",
      "email": "lukabavdaz@gmail.com",
      "commits": 1
    },
    {
      "name": "Nikola Mircic",
      "email": "nikola123mircic@gmail.com",
      "commits": 1
    },
    {
      "name": "Soc Virnyl S. Estela",
      "email": "socvirnyl.estela@gmail.com",
      "commits": 1
    },
    {
      "name": "PatOnTheBack",
      "email": "51241310+PatOnTheBack@users.noreply.github.com",
      "commits": 1
    },
    {
      "name": "vasutomar",
      "email": "vasutomar26@gmail.com",
      "commits": 1
    },
    {
      "name": "Aitor Fidalgo Sánchez",
      "email": "64830228+aitorfi@users.noreply.github.com",
      "commits": 1
    },
    {
      "name": "WILFRIED NJANGUI",
      "email": "wilfried.njangui@gmail.com",
      "commits": 1
    }
  ],
  "explanationUrl": {}
}